LICENSE
MANIFEST.in
README.md
ez_setup.py
pandoc_tpp.py
setup.py
pandoc_tpp.egg-info/PKG-INFO
pandoc_tpp.egg-info/SOURCES.txt
pandoc_tpp.egg-info/dependency_links.txt
pandoc_tpp.egg-info/entry_points.txt
pandoc_tpp.egg-info/top_level.txt