Metadata-Version: 1.1
Name: pandoc-tpp
Version: 0.1
Summary: A pandoc template preprocessor.
Home-page: https://github.com/tomduck/pandoc-tpp
Author: Thomas J. Duck
Author-email: tomduck@tomduck.ca
License: GPL
Download-URL: https://github.com/tomduck/pandoc-tpp/tarball/0.1
Keywords: pandoc template preprocessor
Platform: UNKNOWN
Classifier: Development Status :: 4 - Beta
Classifier: Intended Audience :: End Users/Desktop
Classifier: Environment :: Console
Classifier: License :: OSI Approved :: GNU General Public License v3 (GPLv3)
Classifier: Programming Language :: Python
